{
  "source": "GasBuddy",
  "source_url": "https://www.gasbuddy.com/gasprices/wisconsin",
  "state": "Wisconsin",
  "price_date": "03/29/26",
  "scraped_at": "2026-03-29T12:53:09.932088+00:00",
  "statewide": {
    "current_avg": {
      "regular": 3.48,
      "mid_grade": 3.94,
      "premium": 4.465,
      "diesel": 4.623
    },
    "low": {
      "regular": 3.19,
      "mid_grade": 3.36,
      "premium": 3.94,
      "diesel": 4.05
    },
    "high": {
      "regular": 3.59,
      "mid_grade": 4.19,
      "premium": 4.97,
      "diesel": 4.99
    }
  },
  "metros": {
    "Wausau": {
      "current_avg": {
        "regular": 3.576,
        "mid_grade": 3.992,
        "premium": 4.542,
        "diesel": 4.687
      },
      "low": {
        "regular": 3.57,
        "mid_grade": 3.63,
        "premium": 4.33,
        "diesel": 4.58
      },
      "high": {
        "regular": 3.59,
        "mid_grade": 4.19,
        "premium": 4.64,
        "diesel": 4.79
      },
      "station_count": {
        "regular": 20,
        "mid_grade": 20,
        "premium": 20,
        "diesel": 20
      }
    },
    "Eau Claire": {
      "current_avg": {
        "regular": 3.28,
        "mid_grade": 3.701,
        "premium": 4.101,
        "diesel": 4.66
      },
      "low": {
        "regular": 3.19,
        "mid_grade": 3.59,
        "premium": 3.94,
        "diesel": 4.59
      },
      "high": {
        "regular": 3.34,
        "mid_grade": 3.75,
        "premium": 4.19,
        "diesel": 4.69
      },
      "station_count": {
        "regular": 20,
        "mid_grade": 20,
        "premium": 20,
        "diesel": 20
      }
    },
    "Green Bay": {
      "current_avg": {
        "regular": 3.588,
        "mid_grade": 3.961,
        "premium": 4.502,
        "diesel": 4.549
      },
      "low": {
        "regular": 3.57,
        "mid_grade": 3.69,
        "premium": 4.39,
        "diesel": 4.49
      },
      "high": {
        "regular": 3.59,
        "mid_grade": 4.04,
        "premium": 4.59,
        "diesel": 4.65
      },
      "station_count": {
        "regular": 20,
        "mid_grade": 20,
        "premium": 20,
        "diesel": 20
      }
    },
    "Appleton": {
      "current_avg": {
        "regular": 3.558,
        "mid_grade": 3.949,
        "premium": 4.44,
        "diesel": 4.46
      },
      "low": {
        "regular": 3.49,
        "mid_grade": 3.63,
        "premium": 4.29,
        "diesel": 4.39
      },
      "high": {
        "regular": 3.59,
        "mid_grade": 4.09,
        "premium": 4.59,
        "diesel": 4.49
      },
      "station_count": {
        "regular": 20,
        "mid_grade": 20,
        "premium": 20,
        "diesel": 20
      }
    },
    "Madison": {
      "current_avg": {
        "regular": 3.42,
        "mid_grade": 3.958,
        "diesel": 4.568
      },
      "low": {
        "regular": 3.39,
        "mid_grade": 3.89,
        "diesel": 4.49
      },
      "high": {
        "regular": 3.49,
        "mid_grade": 4.03,
        "diesel": 4.59
      },
      "station_count": {
        "regular": 20,
        "mid_grade": 20,
        "diesel": 20
      }
    },
    "Milwaukee": {
      "current_avg": {
        "regular": 3.389,
        "mid_grade": 3.871,
        "premium": 4.106,
        "diesel": 4.282
      },
      "low": {
        "regular": 3.38,
        "mid_grade": 3.79,
        "premium": 3.99,
        "diesel": 4.05
      },
      "high": {
        "regular": 3.39,
        "mid_grade": 3.89,
        "premium": 4.29,
        "diesel": 4.39
      },
      "station_count": {
        "regular": 20,
        "mid_grade": 20,
        "premium": 20,
        "diesel": 20
      }
    },
    "La Crosse": {
      "current_avg": {
        "regular": 3.3,
        "mid_grade": 3.686,
        "premium": 4.51,
        "diesel": 4.768
      },
      "low": {
        "regular": 3.29,
        "mid_grade": 3.36,
        "premium": 4.29,
        "diesel": 4.69
      },
      "high": {
        "regular": 3.39,
        "mid_grade": 4.07,
        "premium": 4.59,
        "diesel": 4.79
      },
      "station_count": {
        "regular": 20,
        "mid_grade": 20,
        "premium": 20,
        "diesel": 20
      }
    },
    "Fond du Lac": {
      "current_avg": {
        "regular": 3.59,
        "mid_grade": 4.082,
        "premium": 4.644,
        "diesel": 4.51
      },
      "low": {
        "regular": 3.59,
        "mid_grade": 3.69,
        "premium": 4.29,
        "diesel": 4.49
      },
      "high": {
        "regular": 3.59,
        "mid_grade": 4.19,
        "premium": 4.79,
        "diesel": 4.59
      },
      "station_count": {
        "regular": 20,
        "mid_grade": 20,
        "premium": 20,
        "diesel": 20
      }
    },
    "Janesville": {
      "current_avg": {
        "regular": 3.522,
        "mid_grade": 3.984,
        "premium": 4.476,
        "diesel": 4.569
      },
      "low": {
        "regular": 3.49,
        "mid_grade": 3.89,
        "premium": 4.29,
        "diesel": 4.49
      },
      "high": {
        "regular": 3.59,
        "mid_grade": 4.07,
        "premium": 4.55,
        "diesel": 4.69
      },
      "station_count": {
        "regular": 20,
        "mid_grade": 20,
        "premium": 20,
        "diesel": 20
      }
    },
    "Kenosha": {
      "current_avg": {
        "regular": 3.493,
        "mid_grade": 4.043,
        "premium": 4.48,
        "diesel": 4.896
      },
      "low": {
        "regular": 3.39,
        "mid_grade": 3.79,
        "premium": 4.19,
        "diesel": 4.64
      },
      "high": {
        "regular": 3.59,
        "mid_grade": 4.09,
        "premium": 4.59,
        "diesel": 4.99
      },
      "station_count": {
        "regular": 20,
        "mid_grade": 20,
        "premium": 20,
        "diesel": 20
      }
    },
    "Oshkosh": {
      "current_avg": {
        "regular": 3.565,
        "mid_grade": 3.955,
        "premium": 4.534,
        "diesel": 4.56
      },
      "low": {
        "regular": 3.49,
        "mid_grade": 3.52,
        "premium": 4.38,
        "diesel": 4.19
      },
      "high": {
        "regular": 3.59,
        "mid_grade": 4.09,
        "premium": 4.59,
        "diesel": 4.69
      },
      "station_count": {
        "regular": 20,
        "mid_grade": 20,
        "premium": 20,
        "diesel": 20
      }
    },
    "Racine": {
      "current_avg": {
        "regular": 3.546,
        "mid_grade": 4.018,
        "premium": 4.382,
        "diesel": 4.542
      },
      "low": {
        "regular": 3.39,
        "mid_grade": 3.79,
        "premium": 4.09,
        "diesel": 4.29
      },
      "high": {
        "regular": 3.59,
        "mid_grade": 4.09,
        "premium": 4.49,
        "diesel": 4.65
      },
      "station_count": {
        "regular": 20,
        "mid_grade": 20,
        "premium": 20,
        "diesel": 20
      }
    },
    "Sheboygan": {
      "current_avg": {
        "regular": 3.509,
        "mid_grade": 4.031,
        "premium": 4.646,
        "diesel": 4.693
      },
      "low": {
        "regular": 3.44,
        "mid_grade": 3.59,
        "premium": 4.52,
        "diesel": 4.49
      },
      "high": {
        "regular": 3.54,
        "mid_grade": 4.17,
        "premium": 4.72,
        "diesel": 4.83
      },
      "station_count": {
        "regular": 20,
        "mid_grade": 20,
        "premium": 20,
        "diesel": 20
      }
    },
    "Superior": {
      "current_avg": {
        "regular": 3.393,
        "mid_grade": 3.84,
        "premium": 4.571,
        "diesel": 4.97
      },
      "low": {
        "regular": 3.33,
        "mid_grade": 3.76,
        "premium": 4.16,
        "diesel": 4.94
      },
      "high": {
        "regular": 3.45,
        "mid_grade": 3.95,
        "premium": 4.97,
        "diesel": 4.99
      },
      "station_count": {
        "regular": 20,
        "mid_grade": 6,
        "premium": 20,
        "diesel": 20
      }
    },
    "Waukesha": {
      "current_avg": {
        "regular": 3.475,
        "mid_grade": 4.032,
        "premium": 4.58,
        "diesel": 4.63
      },
      "low": {
        "regular": 3.39,
        "mid_grade": 3.81,
        "premium": 4.49,
        "diesel": 4.29
      },
      "high": {
        "regular": 3.49,
        "mid_grade": 4.09,
        "premium": 4.59,
        "diesel": 4.69
      },
      "station_count": {
        "regular": 20,
        "mid_grade": 20,
        "premium": 20,
        "diesel": 20
      }
    }
  },
  "priority_metros": [
    "Wausau",
    "Eau Claire",
    "Green Bay",
    "Appleton",
    "Madison",
    "Milwaukee"
  ]
}