{
  "source": "AAA Gas Prices",
  "source_url": "https://gasprices.aaa.com/?state=WI",
  "state": "Wisconsin",
  "price_date": "3/15/26",
  "scraped_at": "2026-03-15T12:43:08.386345+00:00",
  "statewide": {
    "current_avg": {
      "regular": 3.385,
      "mid_grade": 3.84,
      "premium": 4.456,
      "diesel": 4.646
    },
    "yesterday_avg": {
      "regular": 3.368,
      "mid_grade": 3.812,
      "premium": 4.434,
      "diesel": 4.63
    },
    "week_ago_avg": {
      "regular": 3.136,
      "mid_grade": 3.582,
      "premium": 4.205,
      "diesel": 4.259
    },
    "month_ago_avg": {
      "regular": 2.592,
      "mid_grade": 3.119,
      "premium": 3.687,
      "diesel": 3.458
    },
    "year_ago_avg": {
      "regular": 2.881,
      "mid_grade": 3.357,
      "premium": 3.863,
      "diesel": 3.344
    }
  },
  "metros": {
    "Eau Claire": {
      "current_avg": {
        "regular": 3.267,
        "mid_grade": 3.641,
        "premium": 4.31,
        "diesel": 4.628
      },
      "yesterday_avg": {
        "regular": 3.261,
        "mid_grade": 3.646,
        "premium": 4.306,
        "diesel": 4.614
      },
      "week_ago_avg": {
        "regular": 3.119,
        "mid_grade": 3.515,
        "premium": 4.151,
        "diesel": 4.226
      },
      "month_ago_avg": {
        "regular": 2.421,
        "mid_grade": 2.797,
        "premium": 3.482,
        "diesel": 3.457
      },
      "year_ago_avg": {
        "regular": 2.927,
        "mid_grade": 3.383,
        "premium": 3.868,
        "diesel": 3.438
      }
    },
    "Green Bay": {
      "current_avg": {
        "regular": 3.441,
        "mid_grade": 3.956,
        "premium": 4.553,
        "diesel": 4.636
      },
      "yesterday_avg": {
        "regular": 3.419,
        "mid_grade": 3.894,
        "premium": 4.529,
        "diesel": 4.631
      },
      "week_ago_avg": {
        "regular": 3.123,
        "mid_grade": 3.59,
        "premium": 4.235,
        "diesel": 4.255
      },
      "month_ago_avg": {
        "regular": 2.649,
        "mid_grade": 3.224,
        "premium": 3.754,
        "diesel": 3.455
      },
      "year_ago_avg": {
        "regular": 2.919,
        "mid_grade": 3.417,
        "premium": 3.925,
        "diesel": 3.335
      }
    },
    "Janesville-Beloit": {
      "current_avg": {
        "regular": 3.384,
        "mid_grade": 3.873,
        "premium": 4.461,
        "diesel": 4.606
      },
      "yesterday_avg": {
        "regular": 3.373,
        "mid_grade": 3.8,
        "premium": 4.427,
        "diesel": 4.599
      },
      "week_ago_avg": {
        "regular": 3.152,
        "mid_grade": 3.608,
        "premium": 4.209,
        "diesel": 4.271
      },
      "month_ago_avg": {
        "regular": 2.478,
        "mid_grade": 3.014,
        "premium": 3.563,
        "diesel": 3.386
      },
      "year_ago_avg": {
        "regular": 2.804,
        "mid_grade": 3.338,
        "premium": 3.791,
        "diesel": 3.333
      }
    },
    "Madison": {
      "current_avg": {
        "regular": 3.368,
        "mid_grade": 3.869,
        "premium": 4.522,
        "diesel": 4.661
      },
      "yesterday_avg": {
        "regular": 3.368,
        "mid_grade": 3.837,
        "premium": 4.493,
        "diesel": 4.659
      },
      "week_ago_avg": {
        "regular": 3.145,
        "mid_grade": 3.626,
        "premium": 4.299,
        "diesel": 4.285
      },
      "month_ago_avg": {
        "regular": 2.615,
        "mid_grade": 3.178,
        "premium": 3.763,
        "diesel": 3.453
      },
      "year_ago_avg": {
        "regular": 2.877,
        "mid_grade": 3.431,
        "premium": 3.88,
        "diesel": 3.363
      }
    },
    "Milwaukee-Waukesha": {
      "current_avg": {
        "regular": 3.372,
        "mid_grade": 3.838,
        "premium": 4.373,
        "diesel": 4.633
      },
      "yesterday_avg": {
        "regular": 3.349,
        "mid_grade": 3.812,
        "premium": 4.351,
        "diesel": 4.623
      },
      "week_ago_avg": {
        "regular": 3.117,
        "mid_grade": 3.581,
        "premium": 4.11,
        "diesel": 4.192
      },
      "month_ago_avg": {
        "regular": 2.559,
        "mid_grade": 3.099,
        "premium": 3.607,
        "diesel": 3.415
      },
      "year_ago_avg": {
        "regular": 2.775,
        "mid_grade": 3.284,
        "premium": 3.767,
        "diesel": 3.309
      }
    },
    "La Crosse (WI only)": {
      "current_avg": {
        "regular": 3.19,
        "mid_grade": 3.571,
        "premium": 4.388,
        "diesel": 4.77
      },
      "yesterday_avg": {
        "regular": 3.194,
        "mid_grade": 3.699,
        "premium": 4.395,
        "diesel": 4.513
      },
      "week_ago_avg": {
        "regular": 3.018,
        "mid_grade": 3.242,
        "premium": 4.237,
        "diesel": 4.473
      },
      "month_ago_avg": {
        "regular": 2.589,
        "mid_grade": 2.839,
        "premium": 3.765,
        "diesel": 3.487
      },
      "year_ago_avg": {
        "regular": 2.994,
        "mid_grade": 3.209,
        "premium": 4.006,
        "diesel": 3.342
      }
    },
    "Appleton": {
      "current_avg": {
        "regular": 3.42,
        "mid_grade": 3.868,
        "premium": 4.482,
        "diesel": 4.593
      },
      "yesterday_avg": {
        "regular": 3.401,
        "mid_grade": 3.835,
        "premium": 4.45,
        "diesel": 4.586
      },
      "week_ago_avg": {
        "regular": 3.102,
        "mid_grade": 3.528,
        "premium": 4.155,
        "diesel": 4.185
      },
      "month_ago_avg": {
        "regular": 2.573,
        "mid_grade": 3.06,
        "premium": 3.661,
        "diesel": 3.405
      },
      "year_ago_avg": {
        "regular": 2.857,
        "mid_grade": 3.374,
        "premium": 3.846,
        "diesel": 3.272
      }
    },
    "Fond du Lac": {
      "current_avg": {
        "regular": 3.361,
        "mid_grade": 3.859,
        "premium": 4.465,
        "diesel": 4.662
      },
      "yesterday_avg": {
        "regular": 3.357,
        "mid_grade": 3.762,
        "premium": 4.419,
        "diesel": 4.629
      },
      "week_ago_avg": {
        "regular": 3.123,
        "mid_grade": 3.538,
        "premium": 4.199,
        "diesel": 4.281
      },
      "month_ago_avg": {
        "regular": 2.587,
        "mid_grade": 3.143,
        "premium": 3.747,
        "diesel": 3.421
      },
      "year_ago_avg": {
        "regular": 2.85,
        "mid_grade": 3.441,
        "premium": 3.918,
        "diesel": 3.225
      }
    },
    "Kenosha County": {
      "current_avg": {
        "regular": 3.38,
        "mid_grade": 3.869,
        "premium": 4.454,
        "diesel": 4.671
      },
      "yesterday_avg": {
        "regular": 3.364,
        "mid_grade": 3.846,
        "premium": 4.447,
        "diesel": 4.668
      },
      "week_ago_avg": {
        "regular": 3.15,
        "mid_grade": 3.638,
        "premium": 4.201,
        "diesel": 4.15
      },
      "month_ago_avg": {
        "regular": 2.582,
        "mid_grade": 3.139,
        "premium": 3.687,
        "diesel": 3.423
      },
      "year_ago_avg": {
        "regular": 2.852,
        "mid_grade": 3.359,
        "premium": 3.876,
        "diesel": 3.534
      }
    },
    "Oshkosh": {
      "current_avg": {
        "regular": 3.385,
        "mid_grade": 3.805,
        "premium": 4.463,
        "diesel": 4.652
      },
      "yesterday_avg": {
        "regular": 3.365,
        "mid_grade": 3.786,
        "premium": 4.451,
        "diesel": 4.622
      },
      "week_ago_avg": {
        "regular": 3.101,
        "mid_grade": 3.526,
        "premium": 4.198,
        "diesel": 4.215
      },
      "month_ago_avg": {
        "regular": 2.57,
        "mid_grade": 3.128,
        "premium": 3.663,
        "diesel": 3.361
      },
      "year_ago_avg": {
        "regular": 2.881,
        "mid_grade": 3.399,
        "premium": 3.877,
        "diesel": 3.394
      }
    },
    "Pierce -St. Croix County": {
      "current_avg": {
        "regular": 3.415,
        "mid_grade": 3.838,
        "premium": 4.421,
        "diesel": 4.786
      },
      "yesterday_avg": {
        "regular": 3.409,
        "mid_grade": 3.832,
        "premium": 4.393,
        "diesel": 4.746
      },
      "week_ago_avg": {
        "regular": 3.201,
        "mid_grade": 3.59,
        "premium": 4.224,
        "diesel": 4.541
      },
      "month_ago_avg": {
        "regular": 2.578,
        "mid_grade": 3.012,
        "premium": 3.628,
        "diesel": 3.614
      },
      "year_ago_avg": {
        "regular": 3.007,
        "mid_grade": 3.438,
        "premium": 3.923,
        "diesel": 3.536
      }
    },
    "Racine": {
      "current_avg": {
        "regular": 3.358,
        "mid_grade": 3.809,
        "premium": 4.341,
        "diesel": 4.665
      },
      "yesterday_avg": {
        "regular": 3.325,
        "mid_grade": 3.785,
        "premium": 4.315,
        "diesel": 4.641
      },
      "week_ago_avg": {
        "regular": 3.102,
        "mid_grade": 3.576,
        "premium": 4.116,
        "diesel": 4.262
      },
      "month_ago_avg": {
        "regular": 2.529,
        "mid_grade": 3.056,
        "premium": 3.563,
        "diesel": 3.422
      },
      "year_ago_avg": {
        "regular": 2.856,
        "mid_grade": 3.363,
        "premium": 3.846,
        "diesel": 3.375
      }
    },
    "Sheboygan": {
      "current_avg": {
        "regular": 3.369,
        "mid_grade": 3.722,
        "premium": 4.454,
        "diesel": 4.614
      },
      "yesterday_avg": {
        "regular": 3.351,
        "mid_grade": 3.783,
        "premium": 4.468,
        "diesel": 4.589
      },
      "week_ago_avg": {
        "regular": 3.108,
        "mid_grade": 3.585,
        "premium": 4.213,
        "diesel": 4.262
      },
      "month_ago_avg": {
        "regular": 2.623,
        "mid_grade": 3.186,
        "premium": 3.771,
        "diesel": 3.383
      },
      "year_ago_avg": {
        "regular": 2.886,
        "mid_grade": 3.465,
        "premium": 3.94,
        "diesel": 3.312
      }
    },
    "Superior": {
      "current_avg": {
        "regular": 3.37,
        "mid_grade": 3.799,
        "premium": 4.533,
        "diesel": 4.722
      },
      "yesterday_avg": {
        "regular": 3.358,
        "mid_grade": 3.799,
        "premium": 4.509,
        "diesel": 4.691
      },
      "week_ago_avg": {
        "regular": 3.257,
        "mid_grade": 3.792,
        "premium": 4.403,
        "diesel": 4.296
      },
      "month_ago_avg": {
        "regular": 2.467,
        "mid_grade": 2.652,
        "premium": 3.561,
        "diesel": 3.674
      },
      "year_ago_avg": {
        "regular": 3.084,
        "mid_grade": 3.619,
        "premium": 3.972,
        "diesel": 3.596
      }
    },
    "Wausau": {
      "current_avg": {
        "regular": 3.483,
        "mid_grade": 3.956,
        "premium": 4.631,
        "diesel": 4.679
      },
      "yesterday_avg": {
        "regular": 3.452,
        "mid_grade": 3.964,
        "premium": 4.617,
        "diesel": 4.678
      },
      "week_ago_avg": {
        "regular": 3.189,
        "mid_grade": 3.698,
        "premium": 4.365,
        "diesel": 4.272
      },
      "month_ago_avg": {
        "regular": 2.68,
        "mid_grade": 3.373,
        "premium": 3.86,
        "diesel": 3.491
      },
      "year_ago_avg": {
        "regular": 2.958,
        "mid_grade": 3.495,
        "premium": 3.945,
        "diesel": 3.271
      }
    }
  },
  "priority_metros": [
    "Wausau",
    "Eau Claire",
    "Green Bay",
    "Appleton",
    "Madison",
    "Milwaukee-Waukesha"
  ]
}